LICENSE
MANIFEST.in
README.rst
setup.py
sqlalchemy_pygresql/__init__.py
sqlalchemy_pygresql/base.py
sqlalchemy_pygresql.egg-info/PKG-INFO
sqlalchemy_pygresql.egg-info/SOURCES.txt
sqlalchemy_pygresql.egg-info/dependency_links.txt
sqlalchemy_pygresql.egg-info/entry_points.txt
sqlalchemy_pygresql.egg-info/not-zip-safe
sqlalchemy_pygresql.egg-info/requires.txt
sqlalchemy_pygresql.egg-info/top_level.txt