Metadata-Version: 1.1
Name: sqlalchemy_pygresql
Version: 1.0.1
Summary: PyGreSQL dialect for SQLAlchemy
Home-page: https://github.com/kaolin/sqlalchemy-pygresql
Author: Kaolin Imago Fire
Author-email: sqlalchemypygresql_spam@erif.org
License: Apache 2.0
Keywords: PyGreSQL PostgreSQL SQLAlchemy
Platform: UNKNOWN
Classifier: Development Status :: 5 - Production/Stable
Classifier: Intended Audience :: Developers
Classifier: License :: OSI Approved :: Apache Software License
Classifier: Natural Language :: English
Classifier: Operating System :: OS Independent
Classifier: Programming Language :: Python :: 2
Classifier: Programming Language :: Python :: 2.4
Classifier: Programming Language :: Python :: 2.5
Classifier: Programming Language :: Python :: 2.6
Classifier: Programming Language :: Python :: 2.7
Classifier: Programming Language :: Python :: 3
Classifier: Programming Language :: Python :: 3.4
Classifier: Topic :: Database
Classifier: Topic :: Software Development :: Libraries :: Python Modules
